{
    "status": "ok",
    "totalResults": 37,
    "articles": [
        {
            "source": {
                "id": "al-jazeera-english",
                "name": "Al Jazeera English"
            },
            "author": "Al Jazeera",
            "title": "Sean Strickland upsets Israel Adesanya to take UFC middleweight title - Al Jazeera English",
            "description": "The 32-year-old Strickland, who made a stir with controversial comments, wins unanimous five-round decision.",
            "url": "https://www.aljazeera.com/sports/2023/9/10/sean-strickland-upsets-israel-adesanya-to-take-ufc-middleweight-title",
            "urlToImage": "https://www.aljazeera.com/wp-content/uploads/2023/09/2023-09-10T045537Z_1922151780_MT1USATODAY21388199_RTRMADP_3_MMA-UFC-293-ADESANYA-VS-STRICKLAND-1694335718.jpg?resize=1920%2C1440",
            "publishedAt": "2023-09-10T08:55:00Z",
            "content": "American Sean Strickland has stunned Nigerian-born New Zealander Israel Adesanya to take the middleweight title by unanimous decision in the main event of UFC 293, the first Ultimate Fighting Champio… [+3685 chars]"
        },
        {
            "source": {
                "id": "reuters",
                "name": "Reuters"
            },
            "author": "Katya Golubkova, Michel Rose, Manoj Kumar",
            "title": "US, Russia praise G20 summit declaration as meeting heads to close - Reuters",
            "description": "Russia and the U.S. both praised a G20 summit declaration that stopped short of directly criticising Moscow for the war in Ukraine as the bloc's leaders headed into the final day of deliberations on Sunday.",
            "url": "https://www.reuters.com/world/russia-says-g20-declaration-balanced-summit-moves-final-day-2023-09-10/",
            "urlToImage": "https://www.reuters.com/resizer/7N3zJH9HmWAj2ADtWDX2tT3-CkU=/1200x628/smart/filters:quality(80)/cloudfront-us-east-2.images.arcpublishing.com/reuters/ACXTINC7UNMQREELEDRMQAWKZE.jpg",
            "publishedAt": "2023-09-10T07:55:00Z",
            "content": "NEW DELHI, Sept 10 (Reuters) - Russia and the U.S. both praised a G20 summit declaration that stopped short of directly criticising Moscow for the war in Ukraine as the bloc's leaders headed into the… [+3302 chars]"
        },
        {
            "source": {
                "id": null,
                "name": "Euronews"
            },
            "author": null,
            "title": "Ukraine war: Kyiv foils Russian drone attack as Russia destroys Ukrainian boats in Black Sea - Euronews",
            "description": "All the latest developments from the war in Ukraine.",
            "url": "https://www.euronews.com/2023/09/10/ukraine-war-kyiv-foils-russian-drone-attack-as-russia-destroys-ukrainian-boats-in-black-se",
            "urlToImage": "https://static.euronews.com/articles/stories/07/88/40/16/1000x563_cmsv2_839fe1fa-bd2c-505c-895d-13c867d1a44d-7884016.jpg",
            "publishedAt": "2023-09-10T07:51:35Z",
            "content": "All the latest developments from the war in Ukraine.\r\n Spanish aid worker killed in Ukraine - Madrid\r\nA Spanish volunteer aid worker has been killed in Ukraine after her vehicle was hit by a projecti… [+3882 chars]"
        },
        {
            "source": {
                "id": null,
                "name": "Eonline.com"
            },
            "author": "Natalie Finn",
            "title": "Unpacking Kevin Costner's Surprisingly Messy Divorce From Christine Baumgartner - E! NEWS",
            "description": "Divorces are never easy, but the back-and-forth between Kevin Costner and his second wife, Christine Baumgartner, has had more twists than Yellowstone.",
            "url": "https://www.eonline.com/news/1385048/unpacking-kevin-costners-surprisingly-messy-divorce-from-christine-baumgartner",
            "urlToImage": "https://akns-images.eonline.com/eol_images/Entire_Site/202388/cr_1200x1200-230908123751-Kevin_Costner_Christine_Baumgartner_2022VFOscars_GettyImages-1388121244.jpg?fit=around%7C1080:1080&output-quality=90&crop=1080:1080;center,top",
            "publishedAt": "2023-09-10T07:00:00Z",
            "content": "She had been a stay-at-home mom since their eldest child, Cayden, was born in 2007, Baumgartner stated, and her \"marital lifestyle, including that of the children, was consistent with Kevin's longter… [+932 chars]"
        },
        {
            "source": {
                "id": null,
                "name": "Fox Business"
            },
            "author": "Sarah Rumpf-Whitten",
            "title": "Kroger and Albertsons plan to sell over 400 stores in connection with $24.6B merger - Fox Business",
            "description": "Kroger and Albertsons will sell 413 stores to C&S Wholesale Grocers in connection with a proposed $24.6 billion merger announced last October.,",
            "url": "https://www.foxbusiness.com/markets/kroger-albertsons-plan-sell-over-400-stores-connection-24-6-billion-merger",
            "urlToImage": "https://a57.foxnews.com/static.foxbusiness.com/foxbusiness.com/content/uploads/2021/09/0/0/Kroger-fast-delivery-service.jpg?ve=1&tl=1",
            "publishedAt": "2023-09-10T06:33:26Z",
            "content": "Grocery giants Kroger and Albertsons announced their plan to sell more than 400 stores and other assets in connection with a $24.6 billion merger proposed last fall, seeking to clear a path for the g… [+2933 chars]"
        },
        {
            "source": {
                "id": null,
                "name": "[Removed]"
            },
            "author": null,
            "title": "[Removed]",
            "description": "[Removed]",
            "url": "https://removed.com",
            "urlToImage": null,
            "publishedAt": "1970-01-01T00:00:00Z",
            "content": "[Removed]"
        },
        {
            "source": {
                "id": null,
                "name": "Chicago Tribune"
            },
            "author": "Tarot Astrologers",
            "title": "Daily horoscope for September 10, 2023 - Chicago Tribune",
            "description": "Check out your daily horoscope here, provided by Tarot astrologers.",
            "url": "https://www.chicagotribune.com/horoscopes/sns-daily-horoscopes-09102023-20230910-zefmbun5kjaonhl7exjt6gc6ty-story.html",
            "urlToImage": "https://www.chicagotribune.com/resizer/wTsrdLN5g_PkNrvYJtMZd6CpStI=/1200x630/filters:format(jpg):quality(70)/cloudfront-us-east-1.images.arcpublishing.com/tronc/2XWTZZQLK5A6XLZ3X2KE34J2K4.jpg",
            "publishedAt": "2023-09-10T06:00:00Z",
            "content": "It could take a little while to get in the groove of things at present. The Moon starts out by trining mystical Neptune, bringing our dreams along with us even after we've gotten out of bed, then she… [+6077 chars]"
        },
        {
            "source": {
                "id": "cnn",
                "name": "CNN"
            },
            "author": "Jeremy Diamond, Kevin Liptak",
            "title": "Biden heads to Vietnam in latest attempt to draw one of China’s neighbors closer to the US - CNN",
            "description": "President Joe Biden arrived at Chinese leader Xi Jinping’s doorstep on Sunday with a deal in hand to draw yet another one of China’s neighbors closer to the United States.",
            "url": "https://www.cnn.com/2023/09/10/politics/g20-summit-india-biden-vietnam-sunday/index.html",
            "urlToImage": "https://media.cnn.com/api/v1/images/stellar/prod/230908124827-02-g20-biden.jpg?c=16x9&q=w_800,c_fill",
            "publishedAt": "2023-09-10T05:56:00Z",
            "content": "President Joe Biden arrived at Chinese leader Xi Jinpings doorstep on Sunday with a deal in hand to draw yet another one of Chinas neighbors closer to the United States.\r\nIn just the last five months… [+8994 chars]"
        },
        {
            "source": {
                "id": "cnn",
                "name": "CNN"
            },
            "author": "Ivana Kottasová, Eyad Kourdi, Mostafa Salem, Nectar Gan",
            "title": "Nervous Moroccans spend a second night in streets after powerful earthquake kills more than 2,000 - CNN",
            "description": "Terrified Moroccans spent a second night in the streets after a powerful earthquake killed more than 2,000 people, as rescuers race against time to reach trapped victims in remote mountain villages near the epicenter hit hardest by the devastating tremor.",
            "url": "https://www.cnn.com/2023/09/10/africa/morocco-earthquake-day-two-intl-hnk/index.html",
            "urlToImage": "https://media.cnn.com/api/v1/images/stellar/prod/230909064924-10-morocco-earthquake-090923.jpg?c=16x9&q=w_800,c_fill",
            "publishedAt": "2023-09-10T05:28:00Z",
            "content": "Terrified Moroccans spent a second night in the streets after a powerful earthquake killed more than 2,000 people, as rescuers race against time to reach trapped victims in remote mountain villages n… [+5120 chars]"
        },
        {
            "source": {
                "id": null,
                "name": "Tuscaloosa News"
            },
            "author": "Zac Al-Khateeb",
            "title": "Nick Saban postgame news conference: Everything Alabama coach said after Texas loss - Tuscaloosa Magazine",
            "description": "Nick Saban spoke at length about Alabama's loss to Texas. Here's what the Crimson Tide coach had to say:",
            "url": "https://www.tuscaloosanews.com/story/sports/college/sec/2023/09/09/nick-saban-postgame-news-conference-alabama-coach-texas-loss/70814933007/",
            "urlToImage": "https://www.tuscaloosanews.com/gcdn/authoring/authoring-images/2023/09/10/NAAS/70813821007-aem-090923-texas-vs-alabama-8.jpg?crop=2879,1627,x0,y146&width=2879&height=1627&format=pjpg&auto=webp",
            "publishedAt": "2023-09-10T04:12:12Z",
            "content": "<ul><li>Nick Saban addressed numerous aspects of Alabama's loss to Texas in his postgame news conference</li><li>Here's everything the Crimson Tide coach had to say of the Week 2 defeat</li></ul>It t… [+2314 chars]"
        },
        {
            "source": {
                "id": null,
                "name": "NDTV News"
            },
            "author": null,
            "title": "Elon Musk Has A Secret Third Child With Grimes Named Techno Mechanicus, Reveals Biography - NDTV",
            "description": "However, not much is known about him or when he was born, and his identity has been a closely guarded secret.",
            "url": "https://www.ndtv.com/world-news/elon-musk-has-a-secret-third-child-with-grimes-named-techno-mechanicus-reveals-biography-4376185",
            "urlToImage": "https://c.ndtvimg.com/2020-05/sfm1fqp8_elon-musk-and-girlfriend-grimes-afp_625x300_05_May_20.jpg",
            "publishedAt": "2023-09-10T04:06:33Z",
            "content": "Mr Musk now has ten known biological children with three different women.\r\nElon Musk and his ex-partner Grimes share three children, not two as previously believed, according to a new biography about… [+1803 chars]"
        },
        {
            "source": {
                "id": null,
                "name": "CBS Sports"
            },
            "author": "",
            "title": "Tomorrow's Top 25 Today: Texas charges into top three of new college football rankings after stunning Alabama - CBS Sports",
            "description": "Projecting the new AP Top 25 college football rankings after Week 2 of the 2023 season",
            "url": "https://www.cbssports.com/college-football/news/tomorrows-top-25-today-texas-charges-into-top-three-of-new-college-football-rankings-after-stunning-alabama/",
            "urlToImage": "https://sportshub.cbsistatic.com/i/r/2023/09/10/bc5a00e7-18f4-44d8-b9af-df368174a0ec/thumbnail/1200x675/5a52fd89202cca1b2c310835d73e8954/graphic-tt25tw1ut.png",
            "publishedAt": "2023-09-10T03:56:00Z",
            "content": "The new college football rankings are guaranteed to have a new set of teams in the top five after a Week 2 that saw Texas pick up one of the biggest wins we may all season, 34-24 over Alabama at Brya… [+9565 chars]"
        },
        {
            "source": {
                "id": "the-hill",
                "name": "The Hill"
            },
            "author": "Julia Shapero",
            "title": "Gun rights group sues New Mexico over order banning guns in public in Albuquerque - The Hill",
            "description": "A gun rights group sued New Mexico Gov. Michelle Lujan Grisham (D) and other state officials on Saturday over an emergency order banning firearms from being carried in public in Albuquerque. The National Association for Gun Rights, alongside Albuquerque resid…",
            "url": "https://thehill.com/homenews/state-watch/4196309-gun-rights-group-sues-over-new-mexico-gun-order/",
            "urlToImage": "https://thehill.com/wp-content/uploads/sites/2/2023/09/AP23252573965319-e1694313742845.jpg?w=1280",
            "publishedAt": "2023-09-10T02:53:00Z",
            "content": "Skip to content\r\nA gun rights group sued New Mexico Gov. Michelle Lujan Grisham (D) and other state officials on Saturday over an emergency order banning firearms from being carried in public in Albu… [+1634 chars]"
        },
        {
            "source": {
                "id": null,
                "name": "YouTube"
            },
            "author": null,
            "title": "Phoenix breaks heat record for most 110+ degree days - AZFamily | Arizona News",
            "description": "Arizona First Alert Forecast Update at 5 p.m. for Saturday, 9/9/2023.   For more Local News from KPHO:  https://www.azfamily.com/ For more YouTube Content: h...",
            "url": "https://www.youtube.com/watch?v=QMaAMg7-958",
            "urlToImage": "https://i.ytimg.com/vi/QMaAMg7-958/maxresdefault.jpg",
            "publishedAt": "2023-09-10T01:34:31Z",
            "content": null
        },
        {
            "source": {
                "id": "cbs-news",
                "name": "CBS News"
            },
            "author": null,
            "title": "Several wounded when gunmen open fire on convoy in Mexican border town - CBS News",
            "description": "The attack happened on the international bridge that connects the town of Miguel Aleman with Roma, Texas, Mexican officials said.",
            "url": "https://www.cbsnews.com/news/shooting-convoy-mexico-border-town-miguel-aleman-several-hurt-tamaulipas-roma-texas/",
            "urlToImage": "https://assets3.cbsnewsstatic.com/hub/i/r/2021/10/22/ff9c4cb3-8c7b-4180-ae49-596b31dc89b4/thumbnail/1200x630/269009b5bca15082f6e6a3f0f477e1cb/gettyimages-88961749.jpg?v=181d27d1e918a6408b48ea2e220df310",
            "publishedAt": "2023-09-10T00:31:00Z",
            "content": "At least three people were wounded when a convoy of vehicles crossing into Mexico from the U.S. was attacked by armed civilians early Saturday, Mexican authorities said. \r\nThe Tamaulipas state securi… [+1434 chars]"
        },
        {
            "source": {
                "id": "politico",
                "name": "Politico"
            },
            "author": null,
            "title": "UN atomic watchdog warns of threat to nuclear safety as fighting spikes near a plant in Ukraine - POLITICO",
            "description": "The International Atomic Energy Agency said its experts deployed at the Russia-occupied Zaporizhzhia Nuclear Power Plant reported hearing numerous explosions over the past week.",
            "url": "https://www.politico.com/news/2023/09/09/un-atomic-watchdog-nuclear-safety-00114884",
            "urlToImage": "https://static.politico.com/c1/74/a5d1707f49a29d74a4c21cc86d10/russia-ukraine-war-02420.jpg",
            "publishedAt": "2023-09-10T00:28:02Z",
            "content": "He noted that the IAEA team was informed that staff at the nuclear power plant had been reduced temporarily to minimum levels due to concerns of more military activity in the area.\r\nWhatever happens … [+4098 chars]"
        },
        {
            "source": {
                "id": null,
                "name": "NBC Chicago"
            },
            "author": "NBC Chicago Staff",
            "title": "New COVID boosters could roll out in the coming days. Here's what to know - NBC Chicago",
            "description": "The Food and Drug Administration could approve a new COVID-19 booster shot any day now, as part of a trio of vaccines slated to be rolled with the goal of…",
            "url": "https://www.nbcchicago.com/news/local/new-covid-boosters-could-roll-out-in-the-coming-days-heres-what-to-know/3224468/",
            "urlToImage": "https://media.nbcchicago.com/2021/07/COVID.png?resize=1200%2C675&quality=85&strip=all",
            "publishedAt": "2023-09-10T00:06:37Z",
            "content": "The Food and Drug Administration could approve new COVID-19 booster shots any day now, as part of a trio of vaccines slated to be released with the goal of avoiding a \"tripledemic\" of COVID, RSV and … [+2982 chars]"
        },
        {
            "source": {
                "id": null,
                "name": "Variety"
            },
            "author": "Peter Debruge",
            "title": "‘American Fiction’ Review: Jeffrey Wright Takes on Narrow Ideas of Black Representation in Sharp Industry Satire - Variety",
            "description": "In Cord Jefferson’s idea-dense “American Fiction,” no one wants to publish literary professor Thelonious Ellison’s latest novel. Thelonious — or “Monk” to his friends — has delivered a modern rewor…",
            "url": "https://variety.com/2023/film/reviews/american-fiction-review-jeffrey-wright-1235718392/",
            "urlToImage": "https://variety.com/wp-content/uploads/2023/09/american-fiction.jpeg?w=1000&h=563&crop=1",
            "publishedAt": "2023-09-09T23:40:00Z",
            "content": "In Cord Jefferson’s idea-dense “American Fiction,” no one wants to publish literary professor Thelonious Ellison’s latest novel. Thelonious — or “Monk” to his friends — has delivered a modern reworki… [+5566 chars]"
        },
        {
            "source": {
                "id": "abc-news",
                "name": "ABC News"
            },
            "author": "Meredith Deliso",
            "title": "Ashton Kutcher and Mila Kunis apologize over letters of support for Danny Masterson - ABC News",
            "description": "The three actors starred on \"That '70s Show\" together.",
            "url": "https://abcnews.go.com/GMA/Culture/ashton-kutcher-mila-kunis-apologize-letters-support-danny/story?id=103057481",
            "urlToImage": "https://i.abcnewsfe.com/a/88e5ed5c-84de-4f37-a703-d62e2fea4311/ashton-kutcher-mila-kunis-gty-jt-230909_1694292289900_hpMain_16x9.jpg?w=992",
            "publishedAt": "2023-09-09T23:34:05Z",
            "content": "Ashton Kutcher and Mila Kunis issued an apology on Saturday in response to criticism over their character letters in support of convicted rapist Danny Masterson, whom they both starred with on \"That … [+4808 chars]"
        },
        {
            "source": {
                "id": null,
                "name": "YouTube"
            },
            "author": null,
            "title": "NFL DFS Lineups Week 1 Main Slate Picks | Stokastic NFL DFS Lineup Generator - Stokastic DFS - Daily Fantasy Sports Advice",
            "description": "Neil Orfield goes over how he is using the Stokastic NFL DFS lineup generator for the week 1 main slate on DraftKings & FanDuel.NFL Lineup Generator Package ...",
            "url": "https://www.youtube.com/watch?v=9ZfbRnR998M",
            "urlToImage": "https://i.ytimg.com/vi/9ZfbRnR998M/maxresdefault.jpg",
            "publishedAt": "2023-09-09T22:14:24Z",
            "content": null
        }
    ]
}